azure/functions/extension/blob/__init__.py
azure/functions/extension/blob/blobClient.py
azure/functions/extension/blob/blobClientConverter.py
azure/functions/extension/blob/containerClient.py
azure/functions/extension/blob/storageStreamDownloader.py
azfuncblobclient-0.0.6.dist-info/LICENSE
azfuncblobclient-0.0.6.dist-info/METADATA
azfuncblobclient-0.0.6.dist-info/WHEEL
azfuncblobclient-0.0.6.dist-info/top_level.txt
azfuncblobclient-0.0.6.dist-info/RECORD
