Metadata-Version: 2.1
Name: azfuncblobclient
Version: 0.0.6
Summary: Blob Python worker extension for Azure Functions.
Author: Azure Functions team at Microsoft Corp.
Author-email: azurefunctions@microsoft.com
Classifier: Programming Language :: Python :: 3
Classifier: License :: OSI Approved :: MIT License
Classifier: Operating System :: OS Independent
Requires-Python: >=3.7
License-File: LICENSE
Requires-Dist: azfuncbindingbase
Requires-Dist: azure-storage-blob
Provides-Extra: dev
Requires-Dist: flake8 ~=4.0.1 ; extra == 'dev'
Requires-Dist: flake8-logging-format ; extra == 'dev'
Requires-Dist: mypy ; extra == 'dev'
Requires-Dist: pytest ; extra == 'dev'
Requires-Dist: pytest-cov ; extra == 'dev'
Requires-Dist: requests ==2.* ; extra == 'dev'
Requires-Dist: coverage ; extra == 'dev'
